humus/__init__.py
humus_py-0.1.0.dist-info/LICENSE.txt
humus_py-0.1.0.dist-info/METADATA
humus_py-0.1.0.dist-info/WHEEL
humus_py-0.1.0.dist-info/RECORD
