Metadata-Version: 2.1
Name: humus.py
Version: 0.1.0
Summary: A client for the humus composting database
Home-page: https://github.com/timcowlishaw/humus.py
License: AGPL-3.0
Keywords: database,client,permacomputing,compost,decay,experimental
Author: Tim Cowlishaw
Author-email: tim@timcowlishaw.co.uk
Requires-Python: >=3.11,<4.0
Classifier: Development Status :: 3 - Alpha
Classifier: Intended Audience :: Developers
Classifier: License :: OSI Approved :: GNU Affero General Public License v3
Classifier: Programming Language :: Python :: 3
Classifier: Programming Language :: Python :: 3.11
Classifier: Programming Language :: Python :: 3.12
Classifier: Topic :: Database :: Front-Ends
Classifier: Topic :: Games/Entertainment
Requires-Dist: requests (>=2.32.3,<3.0.0)
Project-URL: Repository, https://github.com/timcowlishaw/humus.py
